<?xml version="1.0" encoding="UTF-8" ?>
<dec TypeName="m1"><DataSet><Header><ENT_NAME /><FISCCOD_FISC>07</FISCCOD_FISC><CUATM>0140</CUATM><STREET>Grenoble 106</STREET><STREET_NR /><CAEM>G4633</CAEM><CUIIO>45454545</CUIIO><IDNO>1234567891234</IDNO><HEAD /><EXECUTOR>Iana Oancea</EXECUTOR><PHONE /><EMAIL>iana.oancea@statistica.gov.md</EMAIL><nalogPeriodType>T/3/2024</nalogPeriodType><nalogPeriodLetter>T</nalogPeriodLetter><TRIM>3</TRIM><YEAR>2024</YEAR></Header><Data><CAP1_CAEM_C2>G4633</CAP1_CAEM_C2><CAP1_CAEM_C3>G4639</CAP1_CAEM_C3><CAP1_CAEM_C4>G4711</CAP1_CAEM_C4><CAP1_CAEM_C5>G4621</CAP1_CAEM_C5><CAP1_CAEM_C6 /><CAP1_CAEM_C7 /><CAP1_CAEM_C8 /><CAP1_CAEM_C9 /><CAP1_CAEM_C10 /><CAP1_CAEM_C11 /><CAP1_CAEM_C12 /><CAP1_R10_C1>52</CAP1_R10_C1><CAP1_R10_C2>23</CAP1_R10_C2><CAP1_R10_C3>12</CAP1_R10_C3><CAP1_R10_C4>16</CAP1_R10_C4><CAP1_R10_C5>1</CAP1_R10_C5><CAP1_R10_C6 /><CAP1_R10_C7 /><CAP1_R10_C8 /><CAP1_R10_C9 /><CAP1_R10_C10 /><CAP1_R10_C11 /><CAP1_R10_C12 /><CAP1_R20_C1>3</CAP1_R20_C1><CAP1_R20_C2>2</CAP1_R20_C2><CAP1_R20_C3 /><CAP1_R20_C4>1</CAP1_R20_C4><CAP1_R20_C5 /><CAP1_R20_C6 /><CAP1_R20_C7 /><CAP1_R20_C8 /><CAP1_R20_C9 /><CAP1_R20_C10 /><CAP1_R20_C11 /><CAP1_R20_C12 /><CAP1_R30_C1>54.0</CAP1_R30_C1><CAP1_R30_C2>24.0</CAP1_R30_C2><CAP1_R30_C3>11.6</CAP1_R30_C3><CAP1_R30_C4>17.4</CAP1_R30_C4><CAP1_R30_C5>1.0</CAP1_R30_C5><CAP1_R30_C6 /><CAP1_R30_C7 /><CAP1_R30_C8 /><CAP1_R30_C9 /><CAP1_R30_C10 /><CAP1_R30_C11 /><CAP1_R30_C12 /><CAP1_R31_C1 /><CAP1_R31_C2 /><CAP1_R31_C3 /><CAP1_R31_C4 /><CAP1_R31_C5 /><CAP1_R31_C6 /><CAP1_R31_C7 /><CAP1_R31_C8 /><CAP1_R31_C9 /><CAP1_R31_C10 /><CAP1_R31_C11 /><CAP1_R31_C12 /><CAP1_R40_C1>3.0</CAP1_R40_C1><CAP1_R40_C2>2.0</CAP1_R40_C2><CAP1_R40_C3 /><CAP1_R40_C4>1.0</CAP1_R40_C4><CAP1_R40_C5 /><CAP1_R40_C6 /><CAP1_R40_C7 /><CAP1_R40_C8 /><CAP1_R40_C9 /><CAP1_R40_C10 /><CAP1_R40_C11 /><CAP1_R40_C12 /><CAP1_R50_C1>24.5</CAP1_R50_C1><CAP1_R50_C2>10.3</CAP1_R50_C2><CAP1_R50_C3>5.4</CAP1_R50_C3><CAP1_R50_C4>8.3</CAP1_R50_C4><CAP1_R50_C5>0.5</CAP1_R50_C5><CAP1_R50_C6 /><CAP1_R50_C7 /><CAP1_R50_C8 /><CAP1_R50_C9 /><CAP1_R50_C10 /><CAP1_R50_C11 /><CAP1_R50_C12 /><CAP1_R51_C1>24.3</CAP1_R51_C1><CAP1_R51_C2>10.2</CAP1_R51_C2><CAP1_R51_C3>5.4</CAP1_R51_C3><CAP1_R51_C4>8.2</CAP1_R51_C4><CAP1_R51_C5>0.5</CAP1_R51_C5><CAP1_R51_C6 /><CAP1_R51_C7 /><CAP1_R51_C8 /><CAP1_R51_C9 /><CAP1_R51_C10 /><CAP1_R51_C11 /><CAP1_R51_C12 /><CAP1_R52_C1>0.2</CAP1_R52_C1><CAP1_R52_C2>0.1</CAP1_R52_C2><CAP1_R52_C3 /><CAP1_R52_C4>0.1</CAP1_R52_C4><CAP1_R52_C5 /><CAP1_R52_C6 /><CAP1_R52_C7 /><CAP1_R52_C8 /><CAP1_R52_C9 /><CAP1_R52_C10 /><CAP1_R52_C11 /><CAP1_R52_C12 /><CAP1_R70_C1>2838.9</CAP1_R70_C1><CAP1_R70_C2>1308.3</CAP1_R70_C2><CAP1_R70_C3>559.5</CAP1_R70_C3><CAP1_R70_C4>944.1</CAP1_R70_C4><CAP1_R70_C5>27.0</CAP1_R70_C5><CAP1_R70_C6 /><CAP1_R70_C7 /><CAP1_R70_C8 /><CAP1_R70_C9 /><CAP1_R70_C10 /><CAP1_R70_C11 /><CAP1_R70_C12 /><CAP1_R71_C1>244.7</CAP1_R71_C1><CAP1_R71_C2>121.6</CAP1_R71_C2><CAP1_R71_C3>76.6</CAP1_R71_C3><CAP1_R71_C4>46.5</CAP1_R71_C4><CAP1_R71_C5 /><CAP1_R71_C6 /><CAP1_R71_C7 /><CAP1_R71_C8 /><CAP1_R71_C9 /><CAP1_R71_C10 /><CAP1_R71_C11 /><CAP1_R71_C12 /><CAP1_R72_C1 /><CAP1_R72_C2 /><CAP1_R72_C3 /><CAP1_R72_C4 /><CAP1_R72_C5 /><CAP1_R72_C6 /><CAP1_R72_C7 /><CAP1_R72_C8 /><CAP1_R72_C9 /><CAP1_R72_C10 /><CAP1_R72_C11 /><CAP1_R72_C12 /><CAP1_R73_C1>165.7</CAP1_R73_C1><CAP1_R73_C2>143.2</CAP1_R73_C2><CAP1_R73_C3 /><CAP1_R73_C4>22.5</CAP1_R73_C4><CAP1_R73_C5 /><CAP1_R73_C6 /><CAP1_R73_C7 /><CAP1_R73_C8 /><CAP1_R73_C9 /><CAP1_R73_C10 /><CAP1_R73_C11 /><CAP1_R73_C12 /><CAP1_R74_C1 /><CAP1_R74_C2 /><CAP1_R74_C3 /><CAP1_R74_C4 /><CAP1_R74_C5 /><CAP1_R74_C6 /><CAP1_R74_C7 /><CAP1_R74_C8 /><CAP1_R74_C9 /><CAP1_R74_C10 /><CAP1_R74_C11 /><CAP1_R74_C12 /><CAP1_R120_C1>16501.2</CAP1_R120_C1><CAP1_R120_C2>16181.9</CAP1_R120_C2><CAP2_CAEM_C2>G4633</CAP2_CAEM_C2><CAP2_CAEM_C3>G4639</CAP2_CAEM_C3><CAP2_CAEM_C4>G4711</CAP2_CAEM_C4><CAP2_CAEM_C5>G4621</CAP2_CAEM_C5><CAP2_CAEM_C6 /><CAP2_CAEM_C7 /><CAP2_CAEM_C8 /><CAP2_CAEM_C9 /><CAP2_CAEM_C10 /><CAP2_CAEM_C11 /><CAP2_CAEM_C12 /><CAP2_R10_C1>51</CAP2_R10_C1><CAP2_R10_C2>22</CAP2_R10_C2><CAP2_R10_C3>11</CAP2_R10_C3><CAP2_R10_C4>17</CAP2_R10_C4><CAP2_R10_C5>1</CAP2_R10_C5><CAP2_R10_C6 /><CAP2_R10_C7 /><CAP2_R10_C8 /><CAP2_R10_C9 /><CAP2_R10_C10 /><CAP2_R10_C11 /><CAP2_R10_C12 /><CAP2_R20_C1 /><CAP2_R20_C2 /><CAP2_R20_C3 /><CAP2_R20_C4 /><CAP2_R20_C5 /><CAP2_R20_C6 /><CAP2_R20_C7 /><CAP2_R20_C8 /><CAP2_R20_C9 /><CAP2_R20_C10 /><CAP2_R20_C11 /><CAP2_R20_C12 /><CAP2_R30_C1 /><CAP2_R30_C2 /><CAP2_R30_C3 /><CAP2_R30_C4 /><CAP2_R30_C5 /><CAP2_R30_C6 /><CAP2_R30_C7 /><CAP2_R30_C8 /><CAP2_R30_C9 /><CAP2_R30_C10 /><CAP2_R30_C11 /><CAP2_R30_C12 /><CAP2_R40_C1 /><CAP2_R40_C2 /><CAP2_R40_C3 /><CAP2_R40_C4 /><CAP2_R40_C5 /><CAP2_R40_C6 /><CAP2_R40_C7 /><CAP2_R40_C8 /><CAP2_R40_C9 /><CAP2_R40_C10 /><CAP2_R40_C11 /><CAP2_R40_C12 /><CAP2_R50_C1 /><CAP2_R50_C2 /><CAP2_R50_C3 /><CAP2_R50_C4 /><CAP2_R50_C5 /><CAP2_R50_C6 /><CAP2_R50_C7 /><CAP2_R50_C8 /><CAP2_R50_C9 /><CAP2_R50_C10 /><CAP2_R50_C11 /><CAP2_R50_C12 /><CAP2_R60_C1 /><CAP2_R60_C2 /><CAP2_R60_C3 /><CAP2_R60_C4 /><CAP2_R60_C5 /><CAP2_R60_C6 /><CAP2_R60_C7 /><CAP2_R60_C8 /><CAP2_R60_C9 /><CAP2_R60_C10 /><CAP2_R60_C11 /><CAP2_R60_C12 /><CAP2_R70_C1>4</CAP2_R70_C1><CAP2_R70_C2>1</CAP2_R70_C2><CAP2_R70_C3>1</CAP2_R70_C3><CAP2_R70_C4>1</CAP2_R70_C4><CAP2_R70_C5>1</CAP2_R70_C5><CAP2_R70_C6 /><CAP2_R70_C7 /><CAP2_R70_C8 /><CAP2_R70_C9 /><CAP2_R70_C10 /><CAP2_R70_C11 /><CAP2_R70_C12 /><CAP2_R80_C1>20</CAP2_R80_C1><CAP2_R80_C2>12</CAP2_R80_C2><CAP2_R80_C3>5</CAP2_R80_C3><CAP2_R80_C4>3</CAP2_R80_C4><CAP2_R80_C5 /><CAP2_R80_C6 /><CAP2_R80_C7 /><CAP2_R80_C8 /><CAP2_R80_C9 /><CAP2_R80_C10 /><CAP2_R80_C11 /><CAP2_R80_C12 /><CAP2_R90_C1>14</CAP2_R90_C1><CAP2_R90_C2>4</CAP2_R90_C2><CAP2_R90_C3>2</CAP2_R90_C3><CAP2_R90_C4>8</CAP2_R90_C4><CAP2_R90_C5 /><CAP2_R90_C6 /><CAP2_R90_C7 /><CAP2_R90_C8 /><CAP2_R90_C9 /><CAP2_R90_C10 /><CAP2_R90_C11 /><CAP2_R90_C12 /><CAP2_R100_C1>6</CAP2_R100_C1><CAP2_R100_C2>1</CAP2_R100_C2><CAP2_R100_C3>3</CAP2_R100_C3><CAP2_R100_C4>2</CAP2_R100_C4><CAP2_R100_C5 /><CAP2_R100_C6 /><CAP2_R100_C7 /><CAP2_R100_C8 /><CAP2_R100_C9 /><CAP2_R100_C10 /><CAP2_R100_C11 /><CAP2_R100_C12 /><CAP2_R110_C1>2</CAP2_R110_C1><CAP2_R110_C2>1</CAP2_R110_C2><CAP2_R110_C3 /><CAP2_R110_C4>1</CAP2_R110_C4><CAP2_R110_C5 /><CAP2_R110_C6 /><CAP2_R110_C7 /><CAP2_R110_C8 /><CAP2_R110_C9 /><CAP2_R110_C10 /><CAP2_R110_C11 /><CAP2_R110_C12 /><CAP2_R120_C1>5</CAP2_R120_C1><CAP2_R120_C2>3</CAP2_R120_C2><CAP2_R120_C3 /><CAP2_R120_C4>2</CAP2_R120_C4><CAP2_R120_C5 /><CAP2_R120_C6 /><CAP2_R120_C7 /><CAP2_R120_C8 /><CAP2_R120_C9 /><CAP2_R120_C10 /><CAP2_R120_C11 /><CAP2_R120_C12 /><CAP2_R160_C1>884.2</CAP2_R160_C1><CAP2_R160_C2>384.0</CAP2_R160_C2><CAP2_R160_C3>172.2</CAP2_R160_C3><CAP2_R160_C4>319.0</CAP2_R160_C4><CAP2_R160_C5>9.0</CAP2_R160_C5><CAP2_R160_C6 /><CAP2_R160_C7 /><CAP2_R160_C8 /><CAP2_R160_C9 /><CAP2_R160_C10 /><CAP2_R160_C11 /><CAP2_R160_C12 /></Data></DataSet></dec>